mirlutils/__init__.py
mirlutils/image/__init__.py
mirlutils/image/get_mass.py
mirlutils/image/utils.py
mirlutils/metrics/__init__.py
mirlutils-0.0.6.dist-info/LICENSE
mirlutils-0.0.6.dist-info/METADATA
mirlutils-0.0.6.dist-info/WHEEL
mirlutils-0.0.6.dist-info/top_level.txt
mirlutils-0.0.6.dist-info/RECORD
